{
    "id": "creative-burnout",
    "name": "Creative Burnout",
    "summary": "A state of physical, emotional, and creative exhaustion caused by prolonged unsustainable creative output that attacks the ability to generate ideas.",
    "explanation": "Creative burnout is the state of physical, emotional, and creative exhaustion caused by prolonged unsustainable creative output. Unlike general burnout, it specifically attacks the ability to generate ideas, find meaning in creative work, and maintain the desire to create at all.\n\nIt is the inevitable endpoint of the feast-famine cycle when the feast phase runs too long or repeats too many times without systemic change.\n\n## Warning Signs\n\n- Ideas feel forced or recycled — the well feels dry\n- Dreading the creative work you used to enjoy\n- Procrastination disguised as 'research' or 'planning'\n- Resentment toward your audience or obligations\n- Physical symptoms: fatigue, insomnia, headaches\n- Comparing yourself to others more than usual\n- Perfectionism escalating — nothing feels good enough to publish\n- Loss of curiosity\n\n## Root Causes\n\n- **No system**: Relying on willpower and inspiration instead of content creation systems\n- **Pace mismatch**: Output rate exceeds recovery rate\n- **Identity fusion**: Self-worth is tied entirely to creative output\n- **Isolation**: Creating alone without feedback or community\n- **Perfectionism**: Every piece must be the best, raising the bar until it is paralyzing\n- **External pressure**: Algorithms, audience expectations, revenue needs dictating pace\n- **No boundaries**: Creation bleeds into all areas of life with no recovery space\n\n## Recovery and Prevention\n\n**Immediate**: Stop completely. Actual rest, not 'productive rest.' Reconnect with why you started creating. Consume without the pressure to create from it.\n\n**Structural (prevention)**: Build content creation systems that do not depend on peak energy. Practice sustainable creation — set a pace you can hold for years. Separate identity from output. Schedule regular breaks and periodic reviews to check in with yourself. Build an idea backlog so you never create from zero.",
    "tags": [
        "well-being",
        "content-creation",
        "mental-health",
        "burnout",
        "creativity"
    ],
    "category": "Well-Being & Happiness",
    "icon": "FaBrain",
    "featured": false,
    "aliases": [
        "Creator Burnout",
        "Content Creator Burnout"
    ],
    "relatedConcepts": [
        "content-creation-systems",
        "sustainable-creation",
        "system-based-productivity",
        "feast-or-famine-cycle",
        "burnout",
        "emotional-burnout"
    ],
    "relatedNotes": [
        "https://notes.dsebastien.net/30+Areas/33+Permanent+notes/33.02+Content/Creative+Burnout"
    ],
    "articles": [],
    "books": [],
    "references": [
        {
            "title": "Obsidian Starter Kit",
            "url": "https://store.dsebastien.net/product/obsidian-starter-kit",
            "type": "other"
        },
        {
            "title": "Knowii Community",
            "url": "https://store.dsebastien.net/product/knowii-community",
            "type": "other"
        },
        {
            "title": "AI Ghostwriter Guide",
            "url": "https://store.dsebastien.net/product/ai-ghostwriter-guide",
            "type": "other"
        }
    ],
    "tutorials": [],
    "datePublished": "2026-03-11",
    "dateModified": "2026-03-11"
}
