{
    "id": "deus-ex-machina",
    "name": "Deus Ex Machina",
    "summary": "An unexpected and contrived resolution that appears without prior setup or foreshadowing, often considered a failure of narrative craft.",
    "explanation": "Deus ex machina (Latin for 'god from the machine') is a plot device where an apparently unsolvable problem is suddenly resolved by an unexpected event, character, ability, or object that had no prior setup. The term originates from ancient Greek theater, where a mechanical crane would lower an actor playing a god onto the stage to resolve the plot. While it worked as a theatrical convention in ancient drama, modern audiences generally view it as a storytelling failure.\n\nThe concept represents the opposite of Chekhov's Gun and proper setup-and-payoff technique. Where Chekhov's Gun demands that introduced elements be used, deus ex machina introduces the solution at the moment of resolution, with no prior establishment. Where setup and payoff creates earned resolutions, deus ex machina imposes unearned ones. The audience feels cheated because the resolution wasn't part of the story's established logic.\n\nExamples are widespread across media. The eagles in The Lord of the Rings are frequently cited (though debated). A character discovering a previously unmentioned ability at the critical moment. A long-lost relative appearing to provide the key information. A storm conveniently destroying the villain's army. In each case, the problem is solved by something outside the story's established framework.\n\nWhat makes deus ex machina problematic isn't just surprise—plot twists are surprising too—but the lack of retroactive coherence. A good twist makes the audience reconsider earlier events ('Oh, that's why they mentioned the basement door was locked!'). Deus ex machina has no such anchoring. There's nothing to reconsider because the solution was never woven into the narrative.\n\nHowever, deus ex machina can be used deliberately and effectively in specific contexts. In comedy, absurd resolutions can be part of the humor (Monty Python). In metafiction, characters may acknowledge the contrivance as commentary on storytelling itself. In some literary traditions, divine intervention is thematically appropriate and expected. The key is intentionality—using it as a choice rather than a crutch.\n\nBeyond storytelling, the concept applies as a metaphor for solutions that bypass established processes. In business, relying on an unexpected investor or windfall rather than sound strategy is a deus ex machina approach. In software, hotfixes that patch symptoms without understanding root causes are the engineering equivalent. The lesson is the same: sustainable solutions come from understanding the system, not from lucky breaks.",
    "tags": [
        "storytelling",
        "writing",
        "principles"
    ],
    "category": "Writing & Content Creation",
    "icon": "FaTheaterMasks",
    "featured": false,
    "aliases": [
        "God from the machine",
        "Contrived resolution",
        "Narrative cop-out"
    ],
    "relatedConcepts": [
        "chekhovs-gun",
        "dramatic-irony",
        "foreshadowing",
        "narrative-economy",
        "narrative-structure",
        "setup-and-payoff",
        "suspense"
    ],
    "relatedNotes": [],
    "references": [
        {
            "title": "Deus ex machina - Wikipedia",
            "url": "https://en.wikipedia.org/wiki/Deus_ex_machina",
            "type": "website"
        },
        {
            "title": "Obsidian Starter Kit",
            "url": "https://store.dsebastien.net/product/obsidian-starter-kit",
            "type": "other"
        },
        {
            "title": "Obsidian Starter Course",
            "url": "https://store.dsebastien.net/product/obsidian-starter-course",
            "type": "other"
        },
        {
            "title": "Knowledge Management for Beginners",
            "url": "https://store.dsebastien.net/product/knowledge-management-for-beginners",
            "type": "other"
        },
        {
            "title": "Knowii Community",
            "url": "https://store.dsebastien.net/product/knowii-community",
            "type": "other"
        },
        {
            "title": "AI Ghostwriter Guide",
            "url": "https://store.dsebastien.net/product/ai-ghostwriter-guide",
            "type": "other"
        }
    ],
    "articles": [],
    "books": [],
    "tutorials": [],
    "datePublished": "2026-03-26",
    "dateModified": "2026-03-26"
}
