{
    "id": "dichotomy",
    "name": "Dichotomy",
    "summary": "Division or contrast between two mutually exclusive and jointly exhaustive things, ideas, or categories.",
    "explanation": "A dichotomy is a division of a whole into two parts that are mutually exclusive (nothing belongs to both) and jointly exhaustive (everything belongs to one or the other). The term comes from the Greek 'dichotomia' meaning 'cutting in two.' Dichotomies are foundational to how humans categorize, compare, and reason about the world.\n\n**Examples of dichotomies**:\n\n- True / false\n- Alive / dead\n- Inside / outside\n- Subject / object\n- Mind / body (Cartesian dualism)\n- Nature / nurture\n- Theory / practice\n- Public / private\n\n**Why dichotomies are useful**:\n\n- **Cognitive efficiency**: Binary categories are easy to process and remember\n- **Clear communication**: They give crisp labels to complex distinctions\n- **Decision support**: Many choices reduce to yes/no, accept/reject\n- **Logical foundation**: Classical logic and computing rest on binary values\n- **Conceptual leverage**: Pairing a concept with its opposite often clarifies both\n\n**Why dichotomies can mislead**:\n\nWhile genuine dichotomies exist (a number is either even or odd, a switch is on or off), many apparent dichotomies are actually continuums or richer structures. Forcing reality into binary buckets when it doesn't fit produces:\n\n- **False dichotomies**: Treating a spectrum as two discrete options (see [[false-dichotomy]])\n- **Loss of nuance**: Erasing the middle ground where most reality lives (see [[grey-thinking]])\n- **Polarization**: Pushing people into camps rather than dialogue\n- **Cognitive distortions**: All-or-nothing thinking that fuels anxiety and rigidity (see [[all-or-nothing-thinking]])\n\n**True vs. false dichotomies**:\n\nA genuine dichotomy satisfies two conditions: mutual exclusion (an item cannot be both) and joint exhaustion (every relevant item must be one or the other). Most everyday 'dichotomies' fail at least one of these tests. 'You're either with us or against us' fails joint exhaustion (neutrality exists). 'Quality vs. speed' often fails mutual exclusion (better processes can deliver both).\n\n**Working with dichotomies**:\n\n1. **Test the binary**: Are the two categories really mutually exclusive and exhaustive?\n2. **Look for the spectrum**: What lies between the two poles?\n3. **Consider third options**: Is there a both/and or neither/nor possibility?\n4. **Use dichotomies as tools**, not truths: A useful binary frame can sharpen thinking without claiming to describe reality fully\n\nFor knowledge workers, recognizing when a dichotomy is genuine vs. constructed is a core critical-thinking skill—it determines whether to choose between options, integrate them, or reject the framing entirely.",
    "tags": [
        "thinking",
        "critical-thinking",
        "mental-models",
        "logic",
        "epistemology"
    ],
    "category": "Thinking",
    "icon": "FaBalanceScale",
    "featured": false,
    "aliases": [
        "Binary distinction",
        "Dualism",
        "Two-way split"
    ],
    "relatedConcepts": [
        "false-dichotomy",
        "dichotomy-of-control",
        "trichotomy-of-control",
        "law-of-excluded-middle",
        "grey-thinking",
        "all-or-nothing-thinking",
        "both-and-thinking",
        "dialectical-thinking",
        "dilemma",
        "paradox",
        "mu"
    ],
    "relatedNotes": [],
    "articles": [],
    "books": [],
    "references": [
        {
            "title": "Dichotomy - Wikipedia",
            "url": "https://en.wikipedia.org/wiki/Dichotomy",
            "type": "website"
        },
        {
            "title": "Obsidian Starter Kit",
            "url": "https://store.dsebastien.net/product/obsidian-starter-kit",
            "type": "other"
        },
        {
            "title": "Knowledge Management for Beginners",
            "url": "https://store.dsebastien.net/product/knowledge-management-for-beginners",
            "type": "other"
        },
        {
            "title": "Knowii Community",
            "url": "https://store.dsebastien.net/product/knowii-community",
            "type": "other"
        },
        {
            "title": "Clarity 101 Workshop",
            "url": "https://store.dsebastien.net/product/clarity-101",
            "type": "other"
        }
    ],
    "tutorials": [],
    "datePublished": "2026-05-18",
    "dateModified": "2026-05-18"
}
