{
    "id": "ego-trip",
    "name": "Ego Trip",
    "summary": "A pattern of behavior driven by an inflated sense of self-importance, where actions serve to bolster one's ego rather than achieve meaningful outcomes.",
    "explanation": "An ego trip is a pattern of behavior where a person acts primarily to inflate or protect their sense of self-importance. The term describes actions, decisions, and communication driven not by genuine purpose but by the need to feel superior, be admired, or assert dominance.\n\n## How Ego Trips Manifest\n\n- **In leadership**: Making decisions to demonstrate authority rather than to serve the team. Micromanaging to feel indispensable. Taking credit for others' work\n- **In knowledge work**: Hoarding information to maintain perceived expertise. Using jargon to signal status rather than communicate clearly\n- **In creativity**: Creating to impress rather than to express. Prioritizing appearance over substance\n- **In conversations**: Dominating discussions, one-upping stories, name-dropping, dismissing others' contributions\n- **In learning**: Refusing to admit ignorance. Avoiding beginner status. Defending existing beliefs against contradicting evidence\n\n## The Cost\n\nEgo trips undermine the very outcomes they seek. The person chasing respect through ego-driven behavior typically earns less of it. Key costs include:\n\n- **Damaged relationships**: People withdraw from ego-driven individuals\n- **Poor decisions**: Ego prioritizes being right over getting it right\n- **Stalled growth**: Learning requires the humility to be a beginner\n- **Wasted energy**: Maintaining a self-image is exhausting\n- **Blind spots**: Ego shields us from feedback we need\n\n## The Antidote\n\nSelf-awareness is the first step. Recognizing when your actions serve your ego rather than your goals allows you to redirect. Practices that help: intellectual humility, seeking feedback, focusing on contribution rather than recognition, and remembering that confidence and ego are not the same thing.",
    "tags": [
        "psychology",
        "self-awareness",
        "leadership",
        "personal-development"
    ],
    "category": "Psychology & Mental Models",
    "icon": "FaBrain",
    "featured": false,
    "aliases": [
        "Ego-Trip",
        "Ego Tripping"
    ],
    "relatedConcepts": [
        "id-ego-and-superego",
        "self-awareness",
        "dunning-kruger-effect",
        "hubris",
        "narcissism",
        "self-deception",
        "self-serving-bias",
        "overconfidence-effect",
        "epistemic-humility",
        "shadow-side",
        "ego-depletion"
    ],
    "relatedNotes": [],
    "articles": [],
    "books": [],
    "references": [
        {
            "title": "Ego trip - Wikipedia",
            "url": "https://en.wikipedia.org/wiki/Ego_trip",
            "type": "website"
        },
        {
            "title": "Obsidian Starter Kit",
            "url": "https://store.dsebastien.net/product/obsidian-starter-kit",
            "type": "other"
        },
        {
            "title": "Knowledge Management for Beginners",
            "url": "https://store.dsebastien.net/product/knowledge-management-for-beginners",
            "type": "other"
        },
        {
            "title": "Knowii Community",
            "url": "https://store.dsebastien.net/product/knowii-community",
            "type": "other"
        },
        {
            "title": "Knowledge Worker Kit",
            "url": "https://store.dsebastien.net/product/knowledge-worker-kit",
            "type": "other"
        },
        {
            "title": "Journaling Deep Dive Workshop",
            "url": "https://store.dsebastien.net/product/journaling-deep-dive",
            "type": "other"
        }
    ],
    "tutorials": [],
    "datePublished": "2026-03-11",
    "dateModified": "2026-03-11"
}
