{
    "id": "strategic-inflection-point",
    "name": "Strategic Inflection Point",
    "summary": "A moment when the fundamentals of a business or industry shift so dramatically that the old strategy no longer works and a new one is required.",
    "explanation": "A Strategic Inflection Point, coined by Intel CEO Andy Grove in his book 'Only the Paranoid Survive,' is a time in the life of a business when its fundamentals are about to change. These changes can be driven by technological breakthroughs, regulatory shifts, competitive disruptions, or changes in customer behavior. The defining feature is that the change is so significant that the existing strategy—no matter how well executed—will lead to decline.\n\nGrove identified the concept through Intel's own near-death experience in the 1980s. When Japanese manufacturers began producing memory chips at lower cost and higher quality, Intel's core business was dying. The strategic inflection point demanded a radical pivot: abandoning memory chips entirely and betting the company on microprocessors. This decision, agonizing at the time, transformed Intel into the dominant processor company for decades.\n\nStrategic inflection points are notoriously difficult to recognize in real time. Grove described the 'valley of death'—the period of confusion and denial between recognizing that something has changed and successfully adapting. Signals are often ambiguous: Is this a temporary disruption or a permanent shift? Leaders must act on incomplete information, and waiting for certainty usually means waiting too long. Grove's famous test: 'If we got kicked out and the board brought in a new CEO, what would they do?' This thought experiment cuts through emotional attachment to the status quo.\n\nExamples abound: the smartphone disrupting Nokia and BlackBerry, streaming disrupting Blockbuster, digital photography disrupting Kodak, and AI disrupting countless industries today. In each case, incumbents had early signals but failed to act decisively. The organizations that survive strategic inflection points share a common trait: leadership willing to cannibalize existing success to capture the next wave.",
    "tags": [
        "strategies",
        "leadership",
        "businesses",
        "decision-making",
        "change-management"
    ],
    "category": "Business & Economics",
    "icon": "FaLightbulb",
    "featured": false,
    "aliases": [
        "Inflection Point",
        "10X Change",
        "Strategic Disruption"
    ],
    "relatedConcepts": [
        "winning-move",
        "creative-destruction",
        "disruptive-innovation",
        "pivot-or-persevere",
        "market-timing",
        "competitive-dynamics",
        "strategic-thinking",
        "paradigm-shifts"
    ],
    "relatedNotes": [],
    "articles": [],
    "books": [
        {
            "title": "Only the Paranoid Survive by Andrew S. Grove",
            "url": "https://www.amazon.com/dp/0385483821?tag=dsebastien00-20"
        }
    ],
    "references": [
        {
            "title": "Strategic inflection point - Wikipedia",
            "url": "https://en.wikipedia.org/wiki/Strategic_inflection_point",
            "type": "website"
        },
        {
            "title": "Knowledge Management for Beginners",
            "url": "https://store.dsebastien.net/product/knowledge-management-for-beginners",
            "type": "other"
        },
        {
            "title": "Knowii Community",
            "url": "https://store.dsebastien.net/product/knowii-community",
            "type": "other"
        },
        {
            "title": "Knowledge Worker Kit",
            "url": "https://store.dsebastien.net/product/knowledge-worker-kit",
            "type": "other"
        },
        {
            "title": "Clarity 101 Workshop",
            "url": "https://store.dsebastien.net/product/clarity-101",
            "type": "other"
        }
    ],
    "tutorials": [],
    "datePublished": "2026-03-10",
    "dateModified": "2026-03-10"
}
